sceleto/__init__.py
sceleto/__init__.pyc
sceleto/colors.py
sceleto/data.py
sceleto/draw.py
sceleto/genes.py
sceleto/genes.pyc
sceleto/markers.py
sceleto/mk_dick.pkl
sceleto/model.py
sceleto/network.py
sceleto/species.py
sceleto/utils.py
sceleto/vdj.py
sceleto/.git/refs/heads/master
sceleto/.git/refs/remotes/origin/master
sceleto/.ipynb_checkpoints/__init__-checkpoint.py
sceleto/__pycache__/__init__.cpython-36.pyc
sceleto/__pycache__/__init__.cpython-38.pyc
sceleto/__pycache__/cc_genes.cpython-36.pyc
sceleto/__pycache__/colors.cpython-36.pyc
sceleto/__pycache__/colors.cpython-38.pyc
sceleto/__pycache__/draw.cpython-36.pyc
sceleto/__pycache__/genes.cpython-36.pyc
sceleto/__pycache__/genes.cpython-38.pyc
sceleto/__pycache__/markers.cpython-36.pyc
sceleto/__pycache__/markers.cpython-38.pyc
sceleto/__pycache__/model.cpython-36.pyc
sceleto/__pycache__/model.cpython-38.pyc
sceleto/__pycache__/network.cpython-36.pyc
sceleto/__pycache__/network.cpython-38.pyc
sceleto/__pycache__/species.cpython-36.pyc
sceleto/__pycache__/species.cpython-38.pyc
sceleto/__pycache__/utils.cpython-36.pyc
sceleto/__pycache__/utils.cpython-38.pyc
sceleto/__pycache__/vdj.cpython-36.pyc
sceleto/data/D01_Human_TF.txt
sceleto/data/D02_CD_genes.txt
sceleto/data/D03_HOM_MouseHumanSequence.rpt.txt
sceleto/data/D04_CellAge_signatures1.csv
sceleto/data/supplementary_tables.xls
sceleto/data/.ipynb_checkpoints/D04_CellAge_signatures1-checkpoint.csv
sceleto/matrix/h5ad_files.txt
sceleto-0.9.8.dist-info/LICENSE
sceleto-0.9.8.dist-info/METADATA
sceleto-0.9.8.dist-info/WHEEL
sceleto-0.9.8.dist-info/top_level.txt
sceleto-0.9.8.dist-info/RECORD
