Metadata-Version: 2.1
Name: sceleto
Version: 0.9.8
Summary: Tool to aid in single cell analysis (temporary description)
Home-page: UNKNOWN
Author: Jongeun Park
Author-email: jp24@kaist.ac.kr
License: LICENSE
Keywords: sceleto,single cell,scRNA-seq
Platform: UNKNOWN
Requires-Python: >=3.7
Requires-Dist: pandas
Requires-Dist: numpy
Requires-Dist: scanpy (>=1.6.1)
Requires-Dist: scipy
Requires-Dist: seaborn
Requires-Dist: networkx
Requires-Dist: python-igraph (==0.9.1)
Requires-Dist: bbknn (==1.4.1)
Requires-Dist: scikit-learn (==0.22)
Requires-Dist: scrublet
Requires-Dist: joblib
Requires-Dist: datetime
Requires-Dist: harmonypy
Requires-Dist: matplotlib
Requires-Dist: geosketch (==0.3)
Requires-Dist: adjustText
Requires-Dist: numba (==0.51.2)
